main_content_extractor/__init__.py
main_content_extractor/main_content_extractor.py
main_content_extractor/trafilatura_extends.py
MainContentExtractor-0.0.4.dist-info/METADATA
MainContentExtractor-0.0.4.dist-info/WHEEL
MainContentExtractor-0.0.4.dist-info/top_level.txt
MainContentExtractor-0.0.4.dist-info/RECORD
