Metadata-Version: 2.1
Name: MainContentExtractor
Version: 0.0.4
Summary: A library to extract the main content from html. Developed for information on LLM and for feeding data into LangChain and LlamaIndex.
Home-page: https://github.com/HawkClaws/main_content_extractor
Author: HawkClaws
License: MIT
Project-URL: Source Code, https://github.com/HawkClaws/main_content_extractor
Requires-Python: >=3.6
Requires-Dist: trafilatura >=1.6.2
Requires-Dist: html2text >=2020.1.16
Requires-Dist: beautifulsoup4 >=4.12.2
